<?xml version="1.0" encoding="utf-8"?>
<!DOCTYPE hibernate-mapping PUBLIC "-//Hibernate/Hibernate Mapping DTD 3.0//EN"
"http://www.hibernate.org/dtd/hibernate-mapping-3.0.dtd">
<!-- 
    Mapping file autogenerated by MyEclipse Persistence Tools
-->
<hibernate-mapping>
    <class name="edu.dufe.oes.bean.EvaluationReceiver" table="evaluation_receiver" catalog="oes">
        <id name="evaluationReceiverID" type="java.lang.Integer">
            <column name="E_RECEIVERID" />
            <generator class="native" />
        </id>
        <many-to-one name="evaluation" class="edu.dufe.oes.bean.Evaluation" fetch="select">
            <column name="EVALUATIONID" />
        </many-to-one>
        <many-to-one name="group" class="edu.dufe.oes.bean.Group" fetch="select">
            <column name="GROUPID" />
        </many-to-one>
        <many-to-one name="student" class="edu.dufe.oes.bean.Student" fetch="select">
            <column name="STUDENTID" />
        </many-to-one>
        <property name="evaluationGrade" type="java.lang.Integer">
            <column name="EVALUATIONGRADE" />
        </property>
        <property name="receiverType" type="java.lang.Integer">
            <column name="RECEIVERTYPE" />
        </property>
        <set name="evaluationResults" inverse="true">
            <key>
                <column name="E_RECEIVERID" />
            </key>
            <one-to-many class="edu.dufe.oes.bean.EvaluationResult" />
        </set>
    </class>
</hibernate-mapping>
